README.txt
setup.cfg
setup.py
gomobile/__init__.py
gomobile.xhtmlmp.egg-info/PKG-INFO
gomobile.xhtmlmp.egg-info/SOURCES.txt
gomobile.xhtmlmp.egg-info/dependency_links.txt
gomobile.xhtmlmp.egg-info/entry_points.txt
gomobile.xhtmlmp.egg-info/namespace_packages.txt
gomobile.xhtmlmp.egg-info/not-zip-safe
gomobile.xhtmlmp.egg-info/requires.txt
gomobile.xhtmlmp.egg-info/top_level.txt
gomobile/xhtmlmp/__init__.py
gomobile/xhtmlmp/tests/__init__.py
gomobile/xhtmlmp/tests/test_img.py
gomobile/xhtmlmp/tests/test_unicode.py
gomobile/xhtmlmp/transformers/__init__.py
gomobile/xhtmlmp/transformers/xhtmlmp_safe.py