Metadata-Version: 1.0
Name: gomobile.xhtmlmp
Version: 0.1
Summary: XHTML mobile profile HTML transformer and cleaner for Pyhton
Home-page: http://www.twinapex.com
Author: Mikko Ohtamaa
Author-email: mikko.ohtamaa@twinapex.com
License: GPL
Keywords: mobile wap safe xhtml profile html cleaner lxml transformer
Platform: UNKNOWN
Classifier: Programming Language :: Python
Classifier: Topic :: Software Development :: Libraries :: Python Modules
Classifier: License :: OSI Approved :: GNU General Public License (GPL)
Classifier: Intended Audience :: Developers
